include/ggml/ggml-alloc.h
include/ggml/ggml.h
lib/static/ggml.lib
sam_cpp/__init__.py
sam_cpp/_core.cp39-win32.pyd
sam_cpp/utils.py
share/pkgconfig/ggml.pc
sam_cpp_python-0.0.1.dist-info/METADATA
sam_cpp_python-0.0.1.dist-info/WHEEL
sam_cpp_python-0.0.1.dist-info/entry_points.txt
sam_cpp_python-0.0.1.dist-info/RECORD
